dscim/__init__.py
dscim/_version.py
dscim/descriptors.py
dscim/menu/__init__.py
dscim/menu/baseline.py
dscim/menu/decorators.py
dscim/menu/equity.py
dscim/menu/main_recipe.py
dscim/menu/risk_aversion.py
dscim/menu/simple_storage.py
dscim/preprocessing/README.md
dscim/preprocessing/__init__.py
dscim/preprocessing/input_damages.py
dscim/preprocessing/midprocessing.py
dscim/preprocessing/preprocessing.py
dscim/utils/__init__.py
dscim/utils/functions.py
dscim/utils/menu_runs.py
dscim/utils/rff.py
dscim/utils/utils.py
dscim-0.7.0.dist-info/METADATA
dscim-0.7.0.dist-info/WHEEL
dscim-0.7.0.dist-info/licenses/LICENSE
dscim-0.7.0.dist-info/RECORD
