Metadata-Version: 2.4
Name: dscim
Version: 0.7.0
Summary: Data-Driven Spatial Climate Impact Model core component code
Project-URL: Homepage, https://github.com/ClimateImpactLab/dscim
Project-URL: Documentation, https://ClimateImpactLab.github.io/dscim
Project-URL: Source, https://github.com/ClimateImpactLab/dscim
Project-URL: Bug Tracker, https://github.com/ClimateImpactLab/dscim/issues
License-File: LICENSE
Classifier: Intended Audience :: Science/Research
Classifier: Natural Language :: English
Classifier: Operating System :: OS Independent
Classifier: Programming Language :: Python :: 3
Classifier: Topic :: Scientific/Engineering
Requires-Python: >=3.8
Requires-Dist: dask[array,distributed]
Requires-Dist: h5netcdf
Requires-Dist: impactlab-tools
Requires-Dist: matplotlib
Requires-Dist: netcdf4
Requires-Dist: numpy
Requires-Dist: p-tqdm
Requires-Dist: pandas
Requires-Dist: pyarrow
Requires-Dist: pyyaml
Requires-Dist: requests
Requires-Dist: statsmodels
Requires-Dist: xarray
Requires-Dist: zarr
Provides-Extra: docs
Requires-Dist: mkdocs; extra == 'docs'
Requires-Dist: mkdocs-material; extra == 'docs'
Requires-Dist: mkdocstrings[python]; extra == 'docs'
